exifdata/__init__.py
exifdata/version.txt
exifdata/adapters/__init__.py
exifdata/adapters/exiftool/__init__.py
exifdata/adapters/tiffdata/__init__.py
exifdata/adapters/vips/__init__.py
exifdata/configuration/__init__.py
exifdata/framework/__init__.py
exifdata/framework/adapter.py
exifdata/framework/field.py
exifdata/framework/groupspace.py
exifdata/framework/metadata.py
exifdata/framework/namespace.py
exifdata/framework/structure.py
exifdata/framework/type.py
exifdata/framework/value.py
exifdata/logging/__init__.py
exifdata/models/__init__.py
exifdata/models/exif/__init__.py
exifdata/models/exif/enumerations.py
exifdata/models/exif/structures.py
exifdata/models/exif/types.py
exifdata/models/exif/data/schema.json
exifdata/models/exif/framework/field.py
exifdata/models/iptc/__init__.py
exifdata/models/iptc/enumerations.py
exifdata/models/iptc/structures.py
exifdata/models/iptc/types.py
exifdata/models/iptc/data/schema.json
exifdata/models/iptc/framework/field.py
exifdata/models/iptc/framework/namespace.py
exifdata/models/xmp/__init__.py
exifdata/models/xmp/types.py
exifdata/models/xmp/data/schema.json
exifdata-0.6.4.dist-info/licenses/LICENSE.md
exifdata-0.6.4.dist-info/METADATA
exifdata-0.6.4.dist-info/WHEEL
exifdata-0.6.4.dist-info/top_level.txt
exifdata-0.6.4.dist-info/zip-safe
exifdata-0.6.4.dist-info/RECORD
