Metadata-Version: 2.4
Name: exifdata
Version: 0.6.4
Summary: Streamlined EXIF, IPTC and XMP image metadata creation and parsing.
Author: Daniel Sissman
License-Expression: MIT
Project-URL: documentation, https://github.com/bluebinary/exifdata/blob/main/README.md
Project-URL: changelog, https://github.com/bluebinary/exifdata/blob/main/CHANGELOG.md
Project-URL: repository, https://github.com/bluebinary/exifdata
Project-URL: issues, https://github.com/bluebinary/exifdata/issues
Project-URL: homepage, https://github.com/bluebinary/exifdata
Keywords: image,metadata,embedded,exif,iptc,xmp
Platform: any
Classifier: Programming Language :: Python :: 3
Classifier: Programming Language :: Python :: 3.10
Classifier: Programming Language :: Python :: 3.11
Classifier: Programming Language :: Python :: 3.12
Classifier: Programming Language :: Python :: 3.13
Requires-Python: >=3.10
License-File: LICENSE.md
Requires-Dist: enumerific>=1.0.5
Requires-Dist: caselessly>=1.0.0
Requires-Dist: deliciousbytes>=1.0.4
Requires-Dist: maxml>=1.0.3
Requires-Dist: tiffdata>=0.5.7
Provides-Extra: development
Requires-Dist: black; extra == "development"
Requires-Dist: pytest; extra == "development"
Requires-Dist: pytest-codeblocks; extra == "development"
Requires-Dist: pyflakes; extra == "development"
Provides-Extra: distribution
Requires-Dist: build; extra == "distribution"
Requires-Dist: twine; extra == "distribution"
Requires-Dist: setup; extra == "distribution"
Provides-Extra: pyvips
Requires-Dist: pyvips; extra == "pyvips"
Dynamic: license-file
